<Defs>

    <!--  Bionic tongue  -->
    <HediffDef ParentName="AddedBodyPartBase">
        <defName>BionicTongue</defName>
        <label>bionic tongue</label>
        <labelNoun>a bionic tongue</labelNoun>
        <description>An installed bionic tongue. Made of synthetic smooth-fibers and connected through a neurogel interface, it can match the performance of a natural tongue in speaking, eating, and tasting.</description>
        <descriptionHyperlinks>
            <ThingDef>BionicTongue</ThingDef>
        </descriptionHyperlinks>
        <spawnThingOnRemoved>BionicTongue</spawnThingOnRemoved>
        <addedPartProps>
            <solid>true</solid>
            <partEfficiency>1.0</partEfficiency>
        </addedPartProps>
    </HediffDef>
    <ThingDef ParentName="BodyPartBionicBase">
        <defName>BionicTongue</defName>
        <label>bionic tongue</label>
        <description>An artificial tongue replacement. Made of synthetic smooth-fibers and connected through a neurogel interface, it can match the performance of a natural tongue in speaking, eating, and tasting.</description>
        <descriptionHyperlinks>
            <RecipeDef>InstallBionicTongue</RecipeDef>
        </descriptionHyperlinks>
        <costList>
            <Plasteel>8</Plasteel>
            <ComponentSpacer>2</ComponentSpacer>
        </costList>
    </ThingDef>
    <RecipeDef ParentName="SurgeryInstallBodyPartArtificialBase">
        <defName>InstallBionicTongue</defName>
        <label>install bionic tongue</label>
        <description>Install a bionic tongue.</description>
        <descriptionHyperlinks>
            <ThingDef>BionicTongue</ThingDef>
            <HediffDef>BionicTongue</HediffDef>
        </descriptionHyperlinks>
        <jobString>Installing bionic tongue.</jobString>
        <ingredients>
            <li>
                <filter>
                    <thingDefs>
                        <li>BionicTongue</li>
                    </thingDefs>
                </filter>
                <count>1</count>
            </li>
        </ingredients>
        <fixedIngredientFilter>
            <thingDefs>
                <li>BionicTongue</li>
            </thingDefs>
        </fixedIngredientFilter>
        <appliedOnFixedBodyParts>
            <li>Tongue</li>
        </appliedOnFixedBodyParts>
        <addsHediff>BionicTongue</addsHediff>
    </RecipeDef>
</Defs>